drb/drivers/wms/__init__.py
drb/drivers/wms/_version.py
drb/drivers/wms/factory.py
drb/drivers/wms/wms_nodes.py
drb/exceptions/wms.py
drb/topics/wms/__init__.py
drb/topics/wms/cortex.yml
drb_driver_wms-1.3.0.dist-info/LICENCE.txt
drb_driver_wms-1.3.0.dist-info/METADATA
drb_driver_wms-1.3.0.dist-info/WHEEL
drb_driver_wms-1.3.0.dist-info/entry_points.txt
drb_driver_wms-1.3.0.dist-info/top_level.txt
drb_driver_wms-1.3.0.dist-info/RECORD
