Metadata-Version: 2.1
Name: drb-driver-wms
Version: 1.3.0
Summary: DRB WMS OGC Service driver
Author: GAEL Systems
Author-email: drb-python@gael.fr
License: LGPLv3
Project-URL: Documentation, http://drb-python.gitlab.io/impl/wms
Project-URL: Source, https://gitlab.com/drb-python/impl/wms
Classifier: Programming Language :: Python :: 3.8
Classifier: Environment :: Plugins
Classifier: License :: OSI Approved :: GNU Lesser General Public License v3 (LGPLv3)
Requires-Python: >=3.8
License-File: LICENCE.txt
Requires-Dist: drb-driver-wxs ~=1.3.0
